kit/lib/__init__.py
kit/lib/colorize.py
kit/lib/deep_dict.py
kit/lib/fileseq.py
kit/lib/path.py
vfxtoolkit-0.0.1.dist-info/licenses/LICENSE
vfxtoolkit-0.0.1.dist-info/METADATA
vfxtoolkit-0.0.1.dist-info/WHEEL
vfxtoolkit-0.0.1.dist-info/top_level.txt
vfxtoolkit-0.0.1.dist-info/RECORD
