Metadata-Version: 2.4
Name: vfxtoolkit
Version: 0.0.1
Summary: Suite of tools for visual effects and media production.
Author-email: Gilles de Saint-Aubert <dsagilles@gmail.com>
License-Expression: Apache-2.0
Project-URL: Homepage, https://github.com/vfxtoolkit/vfxtoolkit
Classifier: Development Status :: 1 - Planning
Classifier: Topic :: Multimedia
Classifier: Programming Language :: Python :: 3
Classifier: Operating System :: OS Independent
Requires-Python: >=3.8
License-File: LICENSE
Dynamic: license-file
